barsdiary/__init__.py
barsdiary/aio.py
barsdiary/sync.py
barsdiary/types.py
barsdiary-0.1.5.dist-info/METADATA
barsdiary-0.1.5.dist-info/WHEEL
barsdiary-0.1.5.dist-info/RECORD
