Metadata-Version: 2.1
Name: barsdiary
Version: 0.1.5
Summary: Python library for working with API "БАРС.Web-Образование"
Home-page: https://github.com/mironovmeow/barsdiary
License: MIT
Keywords: python,aiohttp,pydantic,asyncio
Author: mironovmeow
Author-email: 71277890+mironovmeow@users.noreply.github.com
Requires-Python: >=3.8.1,<4.0.0
Classifier: License :: OSI Approved :: MIT License
Classifier: Programming Language :: Python :: 3
Classifier: Programming Language :: Python :: 3.9
Classifier: Programming Language :: Python :: 3.10
Classifier: Programming Language :: Python :: 3.11
Provides-Extra: async
Provides-Extra: sync
Requires-Dist: aiohttp (>=3.8.3,<4.0.0) ; extra == "async"
Requires-Dist: httpx (>=0.23.1,<0.24.0) ; extra == "sync"
Requires-Dist: loguru (>=0.6.0,<0.7.0)
Requires-Dist: pydantic (>=1.10.2,<2.0.0)
Project-URL: Bug Tracker, https://github.com/mironovmeow/barsdiary/issues
Project-URL: Repository, https://github.com/mironovmeow/barsdiary
